rastervision/pipeline/__init__.py
rastervision/pipeline/cli.py
rastervision/pipeline/config.py
rastervision/pipeline/pipeline.py
rastervision/pipeline/pipeline_config.py
rastervision/pipeline/py.typed
rastervision/pipeline/registry.py
rastervision/pipeline/rv_config.py
rastervision/pipeline/utils.py
rastervision/pipeline/verbosity.py
rastervision/pipeline/version.py
rastervision/pipeline/file_system/__init__.py
rastervision/pipeline/file_system/file_system.py
rastervision/pipeline/file_system/http_file_system.py
rastervision/pipeline/file_system/local_file_system.py
rastervision/pipeline/file_system/utils.py
rastervision/pipeline/runner/__init__.py
rastervision/pipeline/runner/inprocess_runner.py
rastervision/pipeline/runner/local_runner.py
rastervision/pipeline/runner/runner.py
rastervision/pipeline_example_plugin1/__init__.py
rastervision/pipeline_example_plugin1/config1.py
rastervision/pipeline_example_plugin1/config2.py
rastervision/pipeline_example_plugin1/sample_pipeline.py
rastervision/pipeline_example_plugin1/sample_pipeline2.py
rastervision/pipeline_example_plugin2/__init__.py
rastervision/pipeline_example_plugin2/config3.py
rastervision/pipeline_example_plugin2/deluxe_message_maker.py
rastervision_pipeline-0.31.1.dist-info/METADATA
rastervision_pipeline-0.31.1.dist-info/WHEEL
rastervision_pipeline-0.31.1.dist-info/entry_points.txt
rastervision_pipeline-0.31.1.dist-info/top_level.txt
rastervision_pipeline-0.31.1.dist-info/RECORD
