Metadata-Version: 2.1
Name: rastervision_pipeline
Version: 0.31.1
Summary: The main rastervision package for configuring, defining, and running pipelines
Home-page: https://github.com/azavea/raster-vision
Author: Azavea
Author-email: info@azavea.com
License: Apache License 2.0
Keywords: raster deep-learning ml computer-vision earth-observation geospatial geospatial-processing
Classifier: Intended Audience :: Developers
Classifier: License :: OSI Approved :: Apache Software License
Classifier: Programming Language :: Python
Classifier: Programming Language :: Python :: 3
Requires-Dist: click
Requires-Dist: pydantic >=2
Requires-Dist: everett
Requires-Dist: everett[ini]
Requires-Dist: six
Requires-Dist: tqdm
Requires-Dist: requests
